{
  "scan_id": "ssp3d_0188",
  "gender": "female",
  "height_cm": 181.55765578148646,
  "body_shape": "Standard",
  "smpl_params": {
    "camera": [
      1.0,
      0.0,
      0.0
    ],
    "pose": [
      0.0,
      0.0,
      0.0,
      0.0,
      0.0,
      0.0,
      0.0,
      0.0,
      0.0,
      0.0,
      0.0,
      0.0,
      0.0,
      0.0,
      0.0,
      0.0,
      0.0,
      0.0,
      0.0,
      0.0,
      0.0,
      0.0,
      0.0,
      0.0,
      0.0,
      0.0,
      0.0,
      0.0,
      0.0,
      0.0,
      0.0,
      0.0,
      0.0,
      0.0,
      0.0,
      0.0,
      0.0,
      0.0,
      0.0,
      0.0,
      0.0,
      0.0,
      0.0,
      0.0,
      0.0,
      0.0,
      0.0,
      0.0,
      0.0,
      0.0,
      0.0,
      0.0,
      0.0,
      0.0,
      0.0,
      0.0,
      0.0,
      0.0,
      0.0,
      0.0,
      0.0,
      0.0,
      0.0,
      0.0,
      0.0,
      0.0,
      0.0,
      0.0,
      0.0,
      0.0,
      0.0,
      0.0
    ],
    "shape": [
      0.23989933729171753,
      -0.8517450094223022,
      0.5613628625869751,
      1.4358609914779663,
      -0.9494181275367737,
      1.4513922929763794,
      -0.2663741409778595,
      0.06679391860961914,
      -0.33987388014793396,
      -0.2794116139411926
    ]
  },
  "measurements": {
    "Chest Round": 106.19744660848637,
    "Waist Round": 89.13960461545545,
    "Hip Round": 100.1461462366667,
    "Thigh Round": 55.19498185417812,
    "Calf Round": 34.851660378066164,
    "Shoulder": 45.59296945104341,
    "Neck Round": 41.71848937119792,
    "Stomach Round": 90.96657914700234,
    "Bicep Round": 32.78653261627057,
    "Wrist Round": 15.743503847514393,
    "Ankle Round": 25.262660584761118
  }
}