{
  "scan_id": "ssp3d_0129",
  "gender": "female",
  "height_cm": 177.20722643433615,
  "body_shape": "Standard",
  "smpl_params": {
    "camera": [
      1.0,
      0.0,
      0.0
    ],
    "pose": [
      0.0,
      0.0,
      0.0,
      0.0,
      0.0,
      0.0,
      0.0,
      0.0,
      0.0,
      0.0,
      0.0,
      0.0,
      0.0,
      0.0,
      0.0,
      0.0,
      0.0,
      0.0,
      0.0,
      0.0,
      0.0,
      0.0,
      0.0,
      0.0,
      0.0,
      0.0,
      0.0,
      0.0,
      0.0,
      0.0,
      0.0,
      0.0,
      0.0,
      0.0,
      0.0,
      0.0,
      0.0,
      0.0,
      0.0,
      0.0,
      0.0,
      0.0,
      0.0,
      0.0,
      0.0,
      0.0,
      0.0,
      0.0,
      0.0,
      0.0,
      0.0,
      0.0,
      0.0,
      0.0,
      0.0,
      0.0,
      0.0,
      0.0,
      0.0,
      0.0,
      0.0,
      0.0,
      0.0,
      0.0,
      0.0,
      0.0,
      0.0,
      0.0,
      0.0,
      0.0,
      0.0,
      0.0
    ],
    "shape": [
      0.6132935285568237,
      0.5017066597938538,
      0.2980433404445648,
      0.5994852781295776,
      0.6349586844444275,
      0.6051452159881592,
      -0.3092007637023926,
      -0.3330366611480713,
      0.1390208899974823,
      -0.4755948483943939
    ]
  },
  "measurements": {
    "Chest Round": 94.87413181837313,
    "Waist Round": 84.50548874408457,
    "Hip Round": 101.24717673500837,
    "Thigh Round": 55.95374062359838,
    "Calf Round": 31.89634510599842,
    "Shoulder": 46.86519454875058,
    "Neck Round": 38.86159166085642,
    "Stomach Round": 83.96564237289851,
    "Bicep Round": 31.49357666939325,
    "Wrist Round": 18.273643530093597,
    "Ankle Round": 20.278340866112607
  }
}