{
  "scan_id": "ssp3d_0106",
  "gender": "female",
  "height_cm": 180.90207456444728,
  "body_shape": "Standard",
  "smpl_params": {
    "camera": [
      1.0,
      0.0,
      0.0
    ],
    "pose": [
      0.0,
      0.0,
      0.0,
      0.0,
      0.0,
      0.0,
      0.0,
      0.0,
      0.0,
      0.0,
      0.0,
      0.0,
      0.0,
      0.0,
      0.0,
      0.0,
      0.0,
      0.0,
      0.0,
      0.0,
      0.0,
      0.0,
      0.0,
      0.0,
      0.0,
      0.0,
      0.0,
      0.0,
      0.0,
      0.0,
      0.0,
      0.0,
      0.0,
      0.0,
      0.0,
      0.0,
      0.0,
      0.0,
      0.0,
      0.0,
      0.0,
      0.0,
      0.0,
      0.0,
      0.0,
      0.0,
      0.0,
      0.0,
      0.0,
      0.0,
      0.0,
      0.0,
      0.0,
      0.0,
      0.0,
      0.0,
      0.0,
      0.0,
      0.0,
      0.0,
      0.0,
      0.0,
      0.0,
      0.0,
      0.0,
      0.0,
      0.0,
      0.0,
      0.0,
      0.0,
      0.0,
      0.0
    ],
    "shape": [
      0.08009752631187439,
      0.7709563374519348,
      0.3943344056606293,
      0.6539876461029053,
      -0.2902495563030243,
      0.44493040442466736,
      0.4539920687675476,
      -0.000922494160477072,
      -0.0668577030301094,
      -0.16534194350242615
    ]
  },
  "measurements": {
    "Chest Round": 107.90989295132822,
    "Waist Round": 83.40573874328567,
    "Hip Round": 88.32379859268907,
    "Thigh Round": 53.648184425080885,
    "Calf Round": 36.53981048022335,
    "Shoulder": 44.26780058859106,
    "Neck Round": 37.18897805150187,
    "Stomach Round": 89.74715231731112,
    "Bicep Round": 29.6122835380076,
    "Wrist Round": 17.004946418932672,
    "Ankle Round": 20.544546359652443
  }
}